swiftagent/__init__.py
swiftagent/__main__.py
swiftagent/cache.py
swiftagent/constants.py
swiftagent/executor.py
swiftagent/actions/__init__.py
swiftagent/actions/base.py
swiftagent/actions/formatter.py
swiftagent/actions/set.py
swiftagent/actions/utils.py
swiftagent/actions/wrapper.py
swiftagent/actions/resources/__init__.py
swiftagent/actions/resources/base.py
swiftagent/actions/resources/wrapper.py
swiftagent/application/__init__.py
swiftagent/application/base.py
swiftagent/application/types.py
swiftagent/client/__init__.py
swiftagent/client/base.py
swiftagent/core/__init__.py
swiftagent/core/embedder.py
swiftagent/core/prompts.py
swiftagent/core/storage.py
swiftagent/core/utilities.py
swiftagent/llm/__init__.py
swiftagent/llm/adapter.py
swiftagent/memory/__init__.py
swiftagent/memory/base.py
swiftagent/memory/long_term.py
swiftagent/memory/semantic.py
swiftagent/memory/utils.py
swiftagent/memory/working.py
swiftagent/persistence/registry.py
swiftagent/prebuilt/actions/__init__.py
swiftagent/prebuilt/actions/duckduckgo.py
swiftagent/prebuilt/actions/exa.py
swiftagent/prebuilt/actions/yfinance.py
swiftagent/prebuilt/reasoning/__init__.py
swiftagent/prebuilt/reasoning/react.py
swiftagent/prebuilt/storage/__init__.py
swiftagent/prebuilt/storage/chroma.py
swiftagent/reasoning/__init__.py
swiftagent/reasoning/base.py
swiftagent/reasoning/salient.py
swiftagent/router/__init__.py
swiftagent/router/base.py
swiftagent/router/output.py
swiftagent/router/types.py
swiftagent/styling/defaults.py
swiftagent/suite/__init__.py
swiftagent/suite/base.py
swiftagent-0.0.5.dist-info/METADATA
swiftagent-0.0.5.dist-info/WHEEL
swiftagent-0.0.5.dist-info/licenses/LICENSE
swiftagent-0.0.5.dist-info/RECORD
