Metadata-Version: 2.4
Name: swiftagent
Version: 0.0.5
Summary: SwiftAgent: Building AI Agents At SCALE
Project-URL: Homepage, https://github.com/BRama10/swiftagent
Project-URL: Repository, https://github.com/BRama10/swiftagent.git
License: Copyright (c) 2025 Openminder Labs
License-File: LICENSE
Keywords: agents,interface,llm
Classifier: Development Status :: 3 - Alpha
Classifier: Intended Audience :: Developers
Classifier: License :: OSI Approved :: MIT License
Classifier: Programming Language :: Python :: 3
Classifier: Programming Language :: Python :: 3.10
Classifier: Topic :: Software Development :: Libraries :: Python Modules
Requires-Python: <3.12,>=3.10
Requires-Dist: aiohttp
Requires-Dist: chromadb
Requires-Dist: cloudpickle
Requires-Dist: fastembed
Requires-Dist: langchain-text-splitters
Requires-Dist: litellm
Requires-Dist: markitdown
Requires-Dist: platformdirs
Requires-Dist: psutil
Requires-Dist: rich
Requires-Dist: sentence-transformers
Requires-Dist: starlette
Requires-Dist: uvicorn
Requires-Dist: websockets
